d3blocks/__init__.py
d3blocks/d3blocks.py
d3blocks/examples.py
d3blocks/utils.py
d3blocks/chord/Chord.py
d3blocks/chord/__init__.py
d3blocks/chord/d3js/__init__.py
d3blocks/chord/d3js/chord.html.j2
d3blocks/chord/d3js/chord.js
d3blocks/circlepacking/Circlepacking.py
d3blocks/circlepacking/__init__.py
d3blocks/circlepacking/d3js/__init__.py
d3blocks/circlepacking/d3js/circlepacking.html.j2
d3blocks/circlepacking/d3js/d3.v6.min.js
d3blocks/circlepacking/d3js/lodash.min.js
d3blocks/elasticgraph/__init__.py
d3blocks/elasticgraph/elasticgraph.py
d3blocks/elasticgraph/d3js/.gitkeep
d3blocks/elasticgraph/d3js/__init__.py
d3blocks/elasticgraph/d3js/d3.v2.js
d3blocks/elasticgraph/d3js/d3graphscript.js
d3blocks/elasticgraph/d3js/elasticgraph.html.j2
d3blocks/elasticgraph/d3js/styles.css
d3blocks/heatmap/Heatmap.py
d3blocks/heatmap/__init__.py
d3blocks/heatmap/d3js/__init__.py
d3blocks/heatmap/d3js/d3.scale.chromatic.v1.min.js
d3blocks/heatmap/d3js/d3.v4.js
d3blocks/heatmap/d3js/heatmap.html.j2
d3blocks/heatmap/d3js/matrix.html.j2
d3blocks/imageslider/Imageslider.py
d3blocks/imageslider/__init__.py
d3blocks/imageslider/d3js/.keep
d3blocks/imageslider/d3js/__init__.py
d3blocks/imageslider/d3js/imageslider.html.j2
d3blocks/imageslider/d3js/jquery-2.1.1.js
d3blocks/imageslider/d3js/main.js
d3blocks/imageslider/d3js/modernizr.js
d3blocks/imageslider/d3js/reset.css
d3blocks/imageslider/d3js/style.css
d3blocks/maps/Maps.py
d3blocks/maps/__init__.py
d3blocks/maps/d3js/__init__.py
d3blocks/maps/d3js/d3.v6.min.js
d3blocks/maps/d3js/maps.html.j2
d3blocks/maps/d3js/world.geojson
d3blocks/matrix/Matrix.py
d3blocks/matrix/__init__.py
d3blocks/matrix/d3js/__init__.py
d3blocks/matrix/d3js/d3.scale.chromatic.v1.min.js
d3blocks/matrix/d3js/d3.v4.js
d3blocks/matrix/d3js/matrix.html.j2
d3blocks/movingbubbles/Movingbubbles.py
d3blocks/movingbubbles/__init__.py
d3blocks/movingbubbles/d3js/__init__.py
d3blocks/movingbubbles/d3js/d3-3-5-5.min.js
d3blocks/movingbubbles/d3js/movingbubbles.html.j2
d3blocks-1.6.1.dist-info/licenses/LICENSE
d3blocks-1.6.1.dist-info/METADATA
d3blocks-1.6.1.dist-info/WHEEL
d3blocks-1.6.1.dist-info/top_level.txt
d3blocks-1.6.1.dist-info/RECORD
