Metadata-Version: 2.4
Name: d3blocks
Version: 1.6.1
Summary: Python package d3blocks.
Author-email: Erdogan Taskesen <erdogant@gmail.com>
License:                     GNU GENERAL PUBLIC LICENSE
Project-URL: Homepage, https://erdogant.github.io/d3blocks
Project-URL: Download, https://github.com/erdogant/d3blocks/archive/{version}.tar.gz
Keywords: Python,
Classifier: Programming Language :: Python :: 3
Classifier: License :: OSI Approved
Classifier: Operating System :: OS Independent
Requires-Python: >=3
License-File: LICENSE
Requires-Dist: numpy
Requires-Dist: colourmap>=1.1.10
Requires-Dist: datazets>=0.1.7
Requires-Dist: d3graph>=2.4.16
Requires-Dist: ismember>=1.0.1
Requires-Dist: pandas
Requires-Dist: tqdm
Requires-Dist: requests
Requires-Dist: jinja2
Dynamic: license-file
